Workbook

Sheet expense
A1: Monthly Expenses till mvp | G1: Expense
A2: Category | B2: Position | C2: Monthly cost | D2: Total | H2: ASAN şəxsi | I2: ASAN iş | J2: sms (otp) | K2: development | L2: Server/Hosting | M2: Ads | N2: Tools & Software | O2: total
A3: Development Costs | B3: Frontend dev | C3: 2000 | D3: =SUM(C3:C5) -> 6000 | G3: 1 | H3: 0 | I3: 0 | J3: 0 | K3: 6000 | L3: 650 | M3: 0 | N3: 0 | O3: =SUM(H3:N3) -> 6650
B4: Backend dev | C4: 2500 | G4: 2 | H4: 0 | I4: 0 | J4: 0 | K4: 6000 | L4: 650 | M4: 0 | N4: 0 | O4: =SUM(H4:N4) -> 6650
B5: UI/UX designer | C5: 1500 | G5: 3 | H5: 0 | I5: 0 | J5: 0 | K5: 6000 | L5: 650 | M5: 0 | N5: 0 | O5: =SUM(H5:N5) -> 6650
A6: Server/Hosting | B6: Web Hosting | C6: 200 | D6: =SUM(C6:C10) -> 650 | G6: 4 | H6: 0 | I6: 0 | J6: 0 | K6: 6000 | L6: 650 | M6: 0 | N6: 0 | O6: =SUM(H6:N6) -> 6650
B7: Database Hosting | C7: 150 | G7: 5 | H7: 0 | I7: 0 | J7: 0 | K7: 6000 | L7: 650 | M7: 0 | N7: 0 | O7: =SUM(H7:N7) -> 6650
B8: Storage | C8: 100 | G8: 6 | H8: 0 | I8: 0 | J8: 0 | K8: 6000 | L8: 650 | M8: 0 | N8: 0 | O8: =SUM(H8:N8) -> 6650
B9: Security & Backup | C9: 100 | G9: 7 | H9: 200 | I9: 200 | J9: =revenue!B3*0.15 -> 300 | K9: 8700 | L9: 900 | M9: 1000 | N9: 70 | O9: =SUM(H9:N9) -> 11370
B10: Miscellaneous Costs | C10: 100 | G10: 8 | H10: 200.5 | I10: 400 | J10: =revenue!B4*0.15 -> 300.75 | K10: 8700 | L10: 900 | M10: 1000 | N10: 70 | O10: =SUM(H10:N10) -> 11571.25
G11: 9 | H11: 157.8 | I11: 558 | J11: =revenue!B5*0.15 -> 236.7 | K11: 8700 | L11: 900 | M11: 1000 | N11: 70 | O11: =SUM(H11:N11) -> 11622.5
A12: Monthly Expenses after mvp | G12: 10 | H12: 127.8 | I12: 686 | J12: =revenue!B6*0.15 -> 191.7 | K12: 8700 | L12: 900 | M12: 1000 | N12: 70 | O12: =SUM(H12:N12) -> 11675.5
A13: Category | B13: Position | C13: Monthly cost | D13: Total | G13: 11 | H13: 84.2 | I13: 770 | J13: =revenue!B7*0.15 -> 126.3 | K13: 8700 | L13: 900 | M13: 1000 | N13: 70 | O13: =SUM(H13:N13) -> 11650.5
A14: Development Costs | B14: Frontend dev | C14: 2000 | D14: =SUM(C14:C18) -> 8700 | G14: 12 | H14: 110.3 | I14: 880 | J14: =revenue!B8*0.15 -> 165.45 | K14: 8700 | L14: 900 | M14: 1000 | N14: 70 | O14: =SUM(H14:N14) -> 11825.75
B15: Backend dev | C15: 2500 | G15: 13 | H15: 162 | I15: 1042 | J15: =revenue!B9*0.15 -> 243 | K15: =(K14*10%)+K14 -> 9570 | L15: =(L14*10%)+L14 -> 990 | M15: =(M14*10%)+M14 -> 1100 | N15: =(N14*10%)+N14 -> 77 | O15: =SUM(H15:N15) -> 13184
B16: UI/UX designer | C16: 1500 | G16: 14 | H16: 68.7 | I16: 1112 | J16: =revenue!B10*0.15 -> 103.05 | K16: 9570 | L16: 990 | M16: 1100 | N16: 77 | O16: =SUM(H16:N16) -> 13020.75
B17: Customer support | C17: 1200 | G17: 15 | H17: 132.1 | I17: 1244 | J17: =revenue!B11*0.15 -> 198.15 | K17: 9570 | L17: 990 | M17: 1100 | N17: 77 | O17: =SUM(H17:N17) -> 13311.25
B18: Marketing specialist | C18: 1500 | G18: 16 | H18: 139.2 | I18: 1382 | J18: =revenue!B12*0.15 -> 208.8 | K18: 9570 | L18: 990 | M18: 1100 | N18: 77 | O18: =SUM(H18:N18) -> 13467
A19: Server/Hosting | B19: Web Hosting | C19: 250 | D19: =SUM(C19:C23) -> 900 | G19: 17 | H19: 162.3 | I19: 1544 | J19: =revenue!B13*0.15 -> 243.45 | K19: 9570 | L19: 990 | M19: 1100 | N19: 77 | O19: =SUM(H19:N19) -> 13686.75
B20: Database Hosting | C20: 200 | G20: 18 | H20: 151.8 | I20: 1696 | J20: =revenue!B14*0.15 -> 227.7 | K20: 9570 | L20: 990 | M20: 1100 | N20: 77 | O20: =SUM(H20:N20) -> 13812.5
B21: Storage | C21: 150 | G21: 19 | H21: 140 | I21: 1836 | J21: =revenue!B15*0.15 -> 210 | K21: 9570 | L21: 990 | M21: 1100 | N21: 77 | O21: =SUM(H21:N21) -> 13923
B22: Security & Backup | C22: 150 | G22: 20 | H22: 124.1 | I22: 1960 | J22: =revenue!B16*0.15 -> 186.15 | K22: 9570 | L22: 990 | M22: 1100 | N22: 77 | O22: =SUM(H22:N22) -> 14007.25
B23: Miscellaneous Costs | C23: 150 | G23: 21 | H23: 180 | I23: 2140 | J23: =revenue!B17*0.15 -> 270 | K23: 9570 | L23: 990 | M23: 1100 | N23: 77 | O23: =SUM(H23:N23) -> 14327
A24: Ads | B24: Digital Ads(Instagram,Facebook,Youtube) | C24: 1000 | D24: 1000 | G24: 22 | H24: 124.7 | I24: 2266 | J24: =revenue!B18*0.15 -> 187.05 | K24: 9570 | L24: 990 | M24: 1100 | N24: 77 | O24: =SUM(H24:N24) -> 14314.75
A25: Tools & Software | B25: Intercom(messaging platform) | C25: 50 | D25: =SUM(C25:C27) -> 70 | G25: 23 | H25: 100.5 | I25: 2366 | J25: =revenue!B19*0.15 -> 150.75 | K25: 9570 | L25: 990 | M25: 1100 | N25: 77 | O25: =SUM(H25:N25) -> 14354.25
B26: Google Analytics | C26: 0 | G26: 24 | H26: 110.3 | I26: 2476 | J26: =revenue!B20*0.15 -> 165.45 | K26: 9570 | L26: 990 | M26: 1100 | N26: 77 | O26: =SUM(H26:N26) -> 14488.75
B27: HubSpot(social media management tool) | C27: 20
A29: Monthly Expenses after 1st year +10%
A30: 11737

Sheet revenue
A1: Revenue
A2: month | B2: subscriptions_monthly | C2: subscriptions_total | D2: premium users | E2: revenue subsc. | F2: ad order | G2: fee for ad | H2: revenue ads | I2: ordered user num | J2: revenue referral | K2: interaction | L2: revenue analytics | M2: total
A3: 7 | B3: 2000 | C3: =B3 -> 2000 | D3: 0 | E3: =D3*5 -> 0 | F3: 0 | G3: 0 | H3: =F3*G3 -> 0 | I3: 100 | J3: =I3*10 -> 1000 | K3: 20000 | L3: 0 | M3: =E3+H3+J3+L3 -> 1000
A4: 8 | B4: 2005 | C4: =B3+B4 -> 4005 | D4: 0 | E4: =D4*5 -> 0 | F4: 0 | G4: 0 | H4: =F4*G4 -> 0 | I4: 200 | J4: =I4*10 -> 2000 | K4: 40050 | L4: 0 | M4: =E4+H4+J4+L4 -> 2000
A5: 9 | B5: 1578 | C5: =C4+B5 -> 5583 | D5: 0 | E5: =D5*5 -> 0 | F5: 0 | G5: 0 | H5: =F5*G5 -> 0 | I5: 279 | J5: =I5*10 -> 2790 | K5: 55830 | L5: 0 | M5: =E5+H5+J5+L5 -> 2790
A6: 10 | B6: 1278 | C6: =C5+B6 -> 6861 | D6: 0 | E6: =D6*5 -> 0 | F6: 2 | G6: 350 | H6: =F6*G6 -> 700 | I6: 343 | J6: =I6*10 -> 3430 | K6: 68610 | L6: 0 | M6: =E6+H6+J6+L6 -> 4130
A7: 11 | B7: 842 | C7: =C6+B7 -> 7703 | D7: 0 | E7: =D7*5 -> 0 | F7: 3 | G7: 350 | H7: =F7*G7 -> 1050 | I7: 385 | J7: =I7*10 -> 3850 | K7: 77030 | L7: 0 | M7: =E7+H7+J7+L7 -> 4900
A8: 12 | B8: 1103 | C8: =C7+B8 -> 8806 | D8: 0 | E8: =D8*5 -> 0 | F8: 2 | G8: 350 | H8: =F8*G8 -> 700 | I8: 440 | J8: =I8*10 -> 4400 | K8: 88060 | L8: 0 | M8: =E8+H8+J8+L8 -> 5100
A9: 13 | B9: 1620 | C9: =C8+B9 -> 10426 | D9: =C9*5% -> 521.3 | E9: =D9*5 -> 2606.5 | F9: 4 | G9: 350 | H9: =F9*G9 -> 1400 | I9: 521 | J9: =I9*10 -> 5210 | K9: 104260 | L9: 10426 | M9: =E9+H9+J9+L9 -> 19642.5
A10: 14 | B10: 687 | C10: =C9+B10 -> 11113 | D10: =C10*5% -> 555.65 | E10: =D10*5 -> 2778.25 | F10: 3 | G10: 350 | H10: =F10*G10 -> 1050 | I10: 556 | J10: =I10*10 -> 5560 | K10: 111130 | L10: 11113 | M10: =E10+H10+J10+L10 -> 20501.25
A11: 15 | B11: 1321 | C11: =C10+B11 -> 12434 | D11: =C11*5% -> 621.7 | E11: =D11*5 -> 3108.5 | F11: 5 | G11: 350 | H11: =F11*G11 -> 1750 | I11: 622 | J11: =I11*10 -> 6220 | K11: 124340 | L11: 12434 | M11: =E11+H11+J11+L11 -> 23512.5
A12: 16 | B12: 1392 | C12: =C11+B12 -> 13826 | D12: =C12*5% -> 691.3 | E12: =D12*5 -> 3456.5 | F12: 5 | G12: 350 | H12: =F12*G12 -> 1750 | I12: 691 | J12: =I12*10 -> 6910 | K12: 138260 | L12: 13826 | M12: =E12+H12+J12+L12 -> 25942.5
A13: 17 | B13: 1623 | C13: =C12+B13 -> 15449 | D13: =C13*5% -> 772.45 | E13: =D13*5 -> 3862.25 | F13: 6 | G13: 350 | H13: =F13*G13 -> 2100 | I13: 772 | J13: =I13*10 -> 7720 | K13: 154490 | L13: 15449 | M13: =E13+H13+J13+L13 -> 29131.25
A14: 18 | B14: 1518 | C14: =C13+B14 -> 16967 | D14: =C14*5% -> 848.35 | E14: =D14*5 -> 4241.75 | F14: 4 | G14: 350 | H14: =F14*G14 -> 1400 | I14: 848 | J14: =I14*10 -> 8480 | K14: 168490 | L14: 16849 | M14: =E14+H14+J14+L14 -> 30970.75
A15: 19 | B15: 1400 | C15: =C14+B15 -> 18367 | D15: =C15*5% -> 918.35 | E15: =D15*5 -> 4591.75 | F15: 5 | G15: 350 | H15: =F15*G15 -> 1750 | I15: 918 | J15: =I15*10 -> 9180 | K15: 180900 | L15: 18090 | M15: =E15+H15+J15+L15 -> 33611.75
A16: 20 | B16: 1241 | C16: =C15+B16 -> 19608 | D16: =C16*5% -> 980.4 | E16: =D16*5 -> 4902 | F16: 5 | G16: 350 | H16: =F16*G16 -> 1750 | I16: 980 | J16: =I16*10 -> 9800 | K16: 198900 | L16: 19890 | M16: =E16+H16+J16+L16 -> 36342
A17: 21 | B17: 1800 | C17: =C16+B17 -> 21408 | D17: =C17*5% -> 1070.4 | E17: =D17*5 -> 5352 | F17: 4 | G17: 450 | H17: =F17*G17 -> 1800 | I17: 1070 | J17: =I17*10 -> 10700 | K17: 211370 | L17: 21137 | M17: =E17+H17+J17+L17 -> 38989
A18: 22 | B18: 1247 | C18: =C17+B18 -> 22655 | D18: =C18*5% -> 1132.75 | E18: =D18*5 -> 5663.75 | F18: 4 | G18: 450 | H18: =F18*G18 -> 1800 | I18: 1133 | J18: =I18*10 -> 11330 | K18: 223840 | L18: 22384 | M18: =E18+H18+J18+L18 -> 41177.75
A19: 23 | B19: 1005 | C19: =C18+B19 -> 23660 | D19: =C19*5% -> 1183 | E19: =D19*5 -> 5915 | F19: 5 | G19: 450 | H19: =F19*G19 -> 2250 | I19: 1183 | J19: =I19*10 -> 11830 | K19: 233890 | L19: 23389 | M19: =E19+H19+J19+L19 -> 43384
A20: 24 | B20: 1103 | C20: =C19+B20 -> 24763 | D20: =C20*5% -> 1238.15 | E20: =D20*5 -> 6190.75 | F20: 6 | G20: 450 | H20: =F20*G20 -> 2700 | I20: 1238 | J20: =I20*10 -> 12380 | K20: 244920 | L20: 24492 | M20: =E20+H20+J20+L20 -> 45762.75

Sheet total
A1: Month | B1: Expenses | C1: Revenue | D1: Budget | F1: initial investment | G1: 90000
A2: 1 | B2: 6650 | C2: 0 | D2: =G1-B2+C2 -> 83350
A3: 2 | B3: 6650 | C3: 0 | D3: =D2-B3+C3 -> 76700
A4: 3 | B4: 6650 | C4: 0 | D4: =D3-B4+C4 -> 70050
A5: 4 | B5: 6650 | C5: 0 | D5: =D4-B5+C5 -> 63400
A6: 5 | B6: 6650 | C6: 0 | D6: =D5-B6+C6 -> 56750
A7: 6 | B7: 6650 | C7: 0 | D7: =D6-B7+C7 -> 50100
A8: 7 | B8: 11370 | C8: 1000 | D8: =D7-B8+C8 -> 39730
A9: 8 | B9: 11571.25 | C9: 2000 | D9: =D8-B9+C9 -> 30158.75
A10: 9 | B10: 11622.5 | C10: 2790 | D10: =D9-B10+C10 -> 21326.25
A11: 10 | B11: 11675.5 | C11: 4130 | D11: =D10-B11+C11 -> 13780.75
A12: 11 | B12: 11650.5 | C12: 4900 | D12: =D11-B12+C12 -> 7030.25
A13: 12 | B13: 11825.75 | C13: 5100 | D13: =D12-B13+C13 -> 304.5
A14: 13 | B14: 13184 | C14: 19642.5 | D14: =D13-B14+C14 -> 6763
... A25: 24 | B25: 14488.75 | C25: 45762.75 | D25: =D24-B25+C25 -> 223375.25
